Metadata-Version: 2.1
Name: StudyToolSerializeLib
Version: 0.1.0
Summary: My first Python library(DATA/SE/DE/RIALIZATION)
Author: Me
License: MIT
